thin_lens/__init__.py
thin_lens/version.py
thin_lens-0.0.3.dist-info/LICENSE
thin_lens-0.0.3.dist-info/METADATA
thin_lens-0.0.3.dist-info/WHEEL
thin_lens-0.0.3.dist-info/top_level.txt
thin_lens-0.0.3.dist-info/RECORD
