Metadata-Version: 2.1
Name: thin_lens
Version: 0.0.3
Summary: Compute the optics of the 'thin'-lens-equation.
Home-page: https://github.com/cherenkov-plenoscope/thin_lens
Author: Sebastian Achim Mueller
Author-email: sebastian-achim.mueller@mpi-hd.mpg.de
Classifier: Programming Language :: Python :: 3
Classifier: License :: OSI Approved :: MIT License
Classifier: Operating System :: OS Independent
Classifier: Natural Language :: English
License-File: LICENSE
